scripts/run_benchmark.py
scripts/run_validation.py
scripts/utils.py
torch_lambda_happy/__init__.py
torch_lambda_happy/dependency_utils.py
torch_lambda_happy/lambda_happy.py
torch_lambda_happy_benchmark/__init__.py
torch_lambda_happy_benchmark/benchmark.py
torch_lambda_happy_benchmark/dependencies.py
torch_lambda_happy_benchmark/lambda_happy_partial.py
torch_lambda_happy_validation/__init__.py
torch_lambda_happy_validation/dependencies.py
torch_lambda_happy_validation/ista_solver.py
torch_lambda_happy_validation/validation.py
torch_lambda_happy-0.1.8.dist-info/METADATA
torch_lambda_happy-0.1.8.dist-info/WHEEL
torch_lambda_happy-0.1.8.dist-info/entry_points.txt
torch_lambda_happy-0.1.8.dist-info/top_level.txt
torch_lambda_happy-0.1.8.dist-info/RECORD
