Metadata-Version: 2.4
Name: torch-lambda-happy
Version: 0.1.8
Summary: Python package exposing the LambdaHappy class
Author-email: Yerly Sevan <sevan.yerly@he-arc.ch>
Requires-Python: >=3.10
Requires-Dist: matplotlib>=3.10.3
Requires-Dist: numpy>=2.2.6
Provides-Extra: benchmark
Requires-Dist: pyqt5; extra == "benchmark"
Provides-Extra: validation
Requires-Dist: pyqt5; extra == "validation"
Requires-Dist: pandas; extra == "validation"
Provides-Extra: all
Requires-Dist: pyqt5; extra == "all"
Requires-Dist: pandas; extra == "all"
